[
    {
        "page": 1,
        "text": "1 \n \nCLASS 1 SAMPLE PAPER 1 \n \n \nSECTION-01   LOGICAL REASONING \n1. Find the next figures in the figure pattern given below. \n \n \n \n \n \n[A] \n \n \n[B] \n \n \n[C] \n \n \n[D] \n \nAns. [D] \n \n2. Complete the number pattern. \n \n \n \n[A] \n \n[B]",
        "images": [
            "static/images/page1_image1.jpeg",
            "static/images/page1_image2.png",
            "static/images/page1_image3.png",
            "static/images/page1_image4.png",
            "static/images/page1_image5.png",
            "static/images/page1_image6.png",
            "static/images/page1_image7.png",
            "static/images/page1_image8.png",
            "static/images/page1_image9.png",
            "static/images/page1_image10.png"
        ],
        "ai_generated_questions": [
            {
                "image": "static/images/page1_image1.jpeg",
                "question": "What does this image show?",
                "caption": "a white and orange check marke",
                "options": [
                    "a white and orange check marke",
                    "A clock",
                    "A grid of shapes",
                    "A number sequence"
                ],
                "answer": "a white and orange check marke"
            },
            {
                "image": "static/images/page1_image2.png",
                "question": "What does this image show?",
                "caption": "a drawing of three flowers with faces",
                "options": [
                    "a drawing of three flowers with faces",
                    "A clock",
                    "A grid of shapes",
                    "A number sequence"
                ],
                "answer": "a drawing of three flowers with faces"
            },
            {
                "image": "static/images/page1_image3.png",
                "question": "What does this image show?",
                "caption": "a drawing of a flower with four petals",
                "options": [
                    "a drawing of a flower with four petals",
                    "A clock",
                    "A grid of shapes",
                    "A number sequence"
                ],
                "answer": "a drawing of a flower with four petals"
            },
            {
                "image": "static/images/page1_image4.png",
                "question": "What does this image show?",
                "caption": "a drawing of two flowers with faces",
                "options": [
                    "a drawing of two flowers with faces",
                    "A clock",
                    "A grid of shapes",
                    "A number sequence"
                ],
                "answer": "a drawing of two flowers with faces"
            },
            {
                "image": "static/images/page1_image5.png",
                "question": "What does this image show?",
                "caption": "two black and white flowers with faces",
                "options": [
                    "two black and white flowers with faces",
                    "A clock",
                    "A grid of shapes",
                    "A number sequence"
                ],
                "answer": "two black and white flowers with faces"
            },
            {
                "image": "static/images/page1_image6.png",
                "question": "What does this image show?",
                "caption": "a drawing of two flowers with faces",
                "options": [
                    "a drawing of two flowers with faces",
                    "A clock",
                    "A grid of shapes",
                    "A number sequence"
                ],
                "answer": "a drawing of two flowers with faces"
            },
            {
                "image": "static/images/page1_image7.png",
                "question": "What does this image show?",
                "caption": "a drawing of two flowers with faces",
                "options": [
                    "a drawing of two flowers with faces",
                    "A clock",
                    "A grid of shapes",
                    "A number sequence"
                ],
                "answer": "a drawing of two flowers with faces"
            },
            {
                "image": "static/images/page1_image8.png",
                "question": "What does this image show?",
                "caption": "a diagram of the four petals of a flower",
                "options": [
                    "a diagram of the four petals of a flower",
                    "A clock",
                    "A grid of shapes",
                    "A number sequence"
                ],
                "answer": "a diagram of the four petals of a flower"
            },
            {
                "image": "static/images/page1_image9.png",
                "question": "What does this image show?",
                "caption": "a flower with the number 15 on it",
                "options": [
                    "a flower with the number 15 on it",
                    "A clock",
                    "A grid of shapes",
                    "A number sequence"
                ],
                "answer": "a flower with the number 15 on it"
            },
            {
                "image": "static/images/page1_image10.png",
                "question": "What does this image show?",
                "caption": "a flower with the number 25 on it",
                "options": [
                    "a flower with the number 25 on it",
                    "A clock",
                    "A grid of shapes",
                    "A number sequence"
                ],
                "answer": "a flower with the number 25 on it"
            }
        ]
    },
    {
        "page": 2,
        "text": "2 \n \n \n[C] \n \n[D] \n \nAns [C] \n \n3. In the questions given below, the series with one or more \nterms figures are missing marked with ‘?’. Choose the \ncorrect option to replace the ‘?’ mark(s). \n \n \n[A] 19 \n[B] 18 \n \n[C] 17 \n[D] 20 \nAns [C] \n \n4. Number of the groups of 9 paper clips (\n) shown here is  \n \n \n[A] 2 \n[B] 3 \n \n[C] 9 \n[D] 27 \nAns [D] \n \n5. How many bananas are kept outside the basket? \n \n \n[A] 1 \n[B] 2 \n \n[C] 3 \n[D] 4",
        "images": [
            "static/images/page2_image1.jpeg",
            "static/images/page2_image2.png",
            "static/images/page2_image3.png",
            "static/images/page2_image4.png",
            "static/images/page2_image5.png",
            "static/images/page2_image6.jpeg",
            "static/images/page2_image7.png"
        ],
        "ai_generated_questions": [
            {
                "image": "static/images/page2_image1.jpeg",
                "question": "What does this image show?",
                "caption": "a white and orange check marke",
                "options": [
                    "a white and orange check marke",
                    "A clock",
                    "A grid of shapes",
                    "A number sequence"
                ],
                "answer": "a white and orange check marke"
            },
            {
                "image": "static/images/page2_image2.png",
                "question": "What does this image show?",
                "caption": "a flower with four petals",
                "options": [
                    "a flower with four petals",
                    "A clock",
                    "A grid of shapes",
                    "A number sequence"
                ],
                "answer": "a flower with four petals"
            },
            {
                "image": "static/images/page2_image3.png",
                "question": "What does this image show?",
                "caption": "a flower with the number 50 on it",
                "options": [
                    "a flower with the number 50 on it",
                    "A clock",
                    "A grid of shapes",
                    "A number sequence"
                ],
                "answer": "a flower with the number 50 on it"
            },
            {
                "image": "static/images/page2_image4.png",
                "question": "What does this image show?",
                "caption": "a black and white image of a line of light",
                "options": [
                    "a black and white image of a line of light",
                    "A clock",
                    "A grid of shapes",
                    "A number sequence"
                ],
                "answer": "a black and white image of a line of light"
            },
            {
                "image": "static/images/page2_image5.png",
                "question": "What does this image show?",
                "caption": "a black and white photo of a metal chain",
                "options": [
                    "a black and white photo of a metal chain",
                    "A clock",
                    "A grid of shapes",
                    "A number sequence"
                ],
                "answer": "a black and white photo of a metal chain"
            },
            {
                "image": "static/images/page2_image6.jpeg",
                "question": "What does this image show?",
                "caption": "a set of metal clips",
                "options": [
                    "a set of metal clips",
                    "A clock",
                    "A grid of shapes",
                    "A number sequence"
                ],
                "answer": "a set of metal clips"
            },
            {
                "image": "static/images/page2_image7.png",
                "question": "What does this image show?",
                "caption": "a basket with bananas and a banana peel",
                "options": [
                    "a basket with bananas and a banana peel",
                    "A clock",
                    "A grid of shapes",
                    "A number sequence"
                ],
                "answer": "a basket with bananas and a banana peel"
            }
        ]
    },
    {
        "page": 3,
        "text": "3 \n \nAns [D] \n \nSECTION-02   MATHEMATICS \n \n6. A programme of children ended at the time shown on the \nclock. At what time did the programme end? \n \n \n[A] 6: 00 \n[B] 5: 20 \n \n[C] 7: 00 \n[D] None of these \nAns [B] \n \n7. Suresh had 112 bookmarks. He gives some bookmarks to her \npupils, he had 13 bookmarks left. How many bookmarks did \nhe give away? \n \n[A] 110 \n[B] 125 \n \n[C] 99 \n[D] 130 \nAns [C]",
        "images": [
            "static/images/page3_image1.jpeg",
            "static/images/page3_image2.png"
        ],
        "ai_generated_questions": [
            {
                "image": "static/images/page3_image1.jpeg",
                "question": "What does this image show?",
                "caption": "a white and orange check marke",
                "options": [
                    "a white and orange check marke",
                    "A clock",
                    "A grid of shapes",
                    "A number sequence"
                ],
                "answer": "a white and orange check marke"
            },
            {
                "image": "static/images/page3_image2.png",
                "question": "What does this image show?",
                "caption": "a clock with a white face and black numbers",
                "options": [
                    "a clock with a white face and black numbers",
                    "A clock",
                    "A grid of shapes",
                    "A number sequence"
                ],
                "answer": "a clock with a white face and black numbers"
            }
        ]
    },
    {
        "page": 4,
        "text": "4 \n \n8. Count and write the amount of money. \n \n \n[A] Rs 70.00 [B] Rs 76.01 \n \n[C] Rs 75.40 [D] Rs 80.04 \nAns [B] \n \n9. Six cats are numbered as follows: \n \n \n \nWhich cat shows the number lying between 40 and 50 and also \nhaving 3 at ones place? \n \n[A] \n \n[B]",
        "images": [
            "static/images/page4_image1.jpeg",
            "static/images/page4_image2.jpeg",
            "static/images/page4_image3.png",
            "static/images/page4_image4.png",
            "static/images/page4_image5.png"
        ],
        "ai_generated_questions": [
            {
                "image": "static/images/page4_image1.jpeg",
                "question": "What does this image show?",
                "caption": "a white and orange check marke",
                "options": [
                    "a white and orange check marke",
                    "A clock",
                    "A grid of shapes",
                    "A number sequence"
                ],
                "answer": "a white and orange check marke"
            },
            {
                "image": "static/images/page4_image2.jpeg",
                "question": "What does this image show?",
                "caption": "a diagram of the different types of liquids",
                "options": [
                    "a diagram of the different types of liquids",
                    "A clock",
                    "A grid of shapes",
                    "A number sequence"
                ],
                "answer": "a diagram of the different types of liquids"
            },
            {
                "image": "static/images/page4_image3.png",
                "question": "What does this image show?",
                "caption": "how to draw a cat",
                "options": [
                    "how to draw a cat",
                    "A clock",
                    "A grid of shapes",
                    "A number sequence"
                ],
                "answer": "how to draw a cat"
            },
            {
                "image": "static/images/page4_image4.png",
                "question": "What does this image show?",
                "caption": "a drawing of a cat",
                "options": [
                    "a drawing of a cat",
                    "A clock",
                    "A grid of shapes",
                    "A number sequence"
                ],
                "answer": "a drawing of a cat"
            },
            {
                "image": "static/images/page4_image5.png",
                "question": "What does this image show?",
                "caption": "a cat with a blue collar and a white collar",
                "options": [
                    "a cat with a blue collar and a white collar",
                    "A clock",
                    "A grid of shapes",
                    "A number sequence"
                ],
                "answer": "a cat with a blue collar and a white collar"
            }
        ]
    },
    {
        "page": 5,
        "text": "5 \n \n \n[C] \n [D] \n \nAns [B] \n \n10. Sonia bought 45 candies. She gave 22 cookies to her sister. \nHow many candies are left with her? \n \n[A] 42 \n[B] 23 \n \n[C] 50 \n[D] 43 \nAns [B] \n \n11. Which of the following is greatest? \n \n \nAns [D] \n \n12. Write ‘+’ or ‘–’ in each \n to complete the number \nsentence. \n \n \n \n[A] +, + \n[B] +, – \n \n[C] –, – \n[D] –, + \nAns [B]",
        "images": [
            "static/images/page5_image1.jpeg",
            "static/images/page5_image2.png",
            "static/images/page5_image3.png",
            "static/images/page5_image4.png",
            "static/images/page5_image5.png"
        ],
        "ai_generated_questions": [
            {
                "image": "static/images/page5_image1.jpeg",
                "question": "What does this image show?",
                "caption": "a white and orange check marke",
                "options": [
                    "a white and orange check marke",
                    "A clock",
                    "A grid of shapes",
                    "A number sequence"
                ],
                "answer": "a white and orange check marke"
            },
            {
                "image": "static/images/page5_image2.png",
                "question": "What does this image show?",
                "caption": "a cat with a blue bow on its neck",
                "options": [
                    "a cat with a blue bow on its neck",
                    "A clock",
                    "A grid of shapes",
                    "A number sequence"
                ],
                "answer": "a cat with a blue bow on its neck"
            },
            {
                "image": "static/images/page5_image3.png",
                "question": "What does this image show?",
                "caption": "a cat with a blue collar and a white tail",
                "options": [
                    "a cat with a blue collar and a white tail",
                    "A clock",
                    "A grid of shapes",
                    "A number sequence"
                ],
                "answer": "a cat with a blue collar and a white tail"
            },
            {
                "image": "static/images/page5_image4.png",
                "question": "What does this image show?",
                "caption": "the three light bulbs are shown in the same pattern",
                "options": [
                    "the three light bulbs are shown in the same pattern",
                    "A clock",
                    "A grid of shapes",
                    "A number sequence"
                ],
                "answer": "the three light bulbs are shown in the same pattern"
            },
            {
                "image": "static/images/page5_image5.png",
                "question": "What does this image show?",
                "caption": "a diagram of the two circles with the same numbers",
                "options": [
                    "a diagram of the two circles with the same numbers",
                    "A clock",
                    "A grid of shapes",
                    "A number sequence"
                ],
                "answer": "a diagram of the two circles with the same numbers"
            }
        ]
    },
    {
        "page": 6,
        "text": "6 \n \n13. \n \n \n \n \nObject _______________ is the heaviest. \n \n[A] 3 \n[B] 5 \n \n[C] 4 \n[D] 1 \nAns [C] \n \nDirection (Q.No.14 & 15): Study the diagram below and \nanswer the questions 14 and 15. \n \n \n14. The length of BD is 1 cm less than the total length of AB \nand AD. \n \nCD is __________ cm longer than BD. \n \n[A] 5 \n[B] 4 \n \n[C] 8 \n[D] 9 \nAns [B] \n \n15. The length of CD is twice that of BC. What is the length of \nall the sides of triangle BCD? \n \n[A] 15 cm \n[B] 31 cm \n \n[C] 42 cm \n[D] 38 cm \nAns [A] \nA\nB\nC\nD\n4 cm\n3 cm\n10 cm",
        "images": [
            "static/images/page6_image1.jpeg",
            "static/images/page6_image2.png",
            "static/images/page6_image3.png"
        ],
        "ai_generated_questions": [
            {
                "image": "static/images/page6_image1.jpeg",
                "question": "What does this image show?",
                "caption": "a white and orange check marke",
                "options": [
                    "a white and orange check marke",
                    "A clock",
                    "A grid of shapes",
                    "A number sequence"
                ],
                "answer": "a white and orange check marke"
            },
            {
                "image": "static/images/page6_image2.png",
                "question": "What does this image show?",
                "caption": "a diagram of a face with a blue eye",
                "options": [
                    "a diagram of a face with a blue eye",
                    "A clock",
                    "A grid of shapes",
                    "A number sequence"
                ],
                "answer": "a diagram of a face with a blue eye"
            },
            {
                "image": "static/images/page6_image3.png",
                "question": "What does this image show?",
                "caption": "a diagram of a triangle with a line of symmetry",
                "options": [
                    "a diagram of a triangle with a line of symmetry",
                    "A clock",
                    "A grid of shapes",
                    "A number sequence"
                ],
                "answer": "a diagram of a triangle with a line of symmetry"
            }
        ]
    },
    {
        "page": 7,
        "text": "7 \n \n16. Which of the following clocks shows 30 minutes after 4 \nO’clock? \n \n[A] \n \n \n[B] \n \n \n[C] \n \n \n[D] \n \nAns [B] \n \n17. Sent gold High School has 453 students. It has 23 more \nstudents than kiddy gold High School. How many students \ndoes kiddy gold High School have? \n \n[A] 400 \n[B] 430 \n \n[C] 403 \n[D] 340 \nAns [B] \n \n12\n6\n5\n4\n3\n2\n1\n11\n10\n9\n8\n7\n12\n6\n5\n4\n3\n2\n1\n11\n10\n9\n8\n7\n12\n6\n5\n4\n3\n2\n1\n11\n10\n9\n8\n7\n12\n6\n5\n4\n3\n2\n1\n11\n10\n9\n8\n7",
        "images": [
            "static/images/page7_image1.jpeg"
        ],
        "ai_generated_questions": [
            {
                "image": "static/images/page7_image1.jpeg",
                "question": "What does this image show?",
                "caption": "a white and orange check marke",
                "options": [
                    "a white and orange check marke",
                    "A clock",
                    "A grid of shapes",
                    "A number sequence"
                ],
                "answer": "a white and orange check marke"
            }
        ]
    },
    {
        "page": 8,
        "text": "8 \n \n18. Tanshu spent Rs 35.70 on a ball and Rs 50.30 on a toy car. \nHow much did he spend altogether? \n \n[A] Rs 80 \n[B] Rs 85 \n \n[C] Rs 58 \n[D] Rs 86 \nAns [D] \n \n19. Which tree has apples more than 6 but less than 9? \n \n[A] \n [B] \n \n \n[C] \n [D] \n \nAns [B] \n \n20. Which abacus shows 15 – 13 = 13? \n \n[A] \n \n[B] \n \n \n[C] \n [D] \n \nAns [C]",
        "images": [
            "static/images/page8_image1.jpeg",
            "static/images/page8_image2.jpeg",
            "static/images/page8_image3.jpeg",
            "static/images/page8_image4.jpeg",
            "static/images/page8_image5.jpeg",
            "static/images/page8_image6.png",
            "static/images/page8_image7.png",
            "static/images/page8_image8.png",
            "static/images/page8_image9.png"
        ],
        "ai_generated_questions": [
            {
                "image": "static/images/page8_image1.jpeg",
                "question": "What does this image show?",
                "caption": "a white and orange check marke",
                "options": [
                    "a white and orange check marke",
                    "A clock",
                    "A grid of shapes",
                    "A number sequence"
                ],
                "answer": "a white and orange check marke"
            },
            {
                "image": "static/images/page8_image2.jpeg",
                "question": "What does this image show?",
                "caption": "a tree with apples on it",
                "options": [
                    "a tree with apples on it",
                    "A clock",
                    "A grid of shapes",
                    "A number sequence"
                ],
                "answer": "a tree with apples on it"
            },
            {
                "image": "static/images/page8_image3.jpeg",
                "question": "What does this image show?",
                "caption": "a tree with apples on it",
                "options": [
                    "a tree with apples on it",
                    "A clock",
                    "A grid of shapes",
                    "A number sequence"
                ],
                "answer": "a tree with apples on it"
            },
            {
                "image": "static/images/page8_image4.jpeg",
                "question": "What does this image show?",
                "caption": "a tree with apples on it",
                "options": [
                    "a tree with apples on it",
                    "A clock",
                    "A grid of shapes",
                    "A number sequence"
                ],
                "answer": "a tree with apples on it"
            },
            {
                "image": "static/images/page8_image5.jpeg",
                "question": "What does this image show?",
                "caption": "a tree with apples on it",
                "options": [
                    "a tree with apples on it",
                    "A clock",
                    "A grid of shapes",
                    "A number sequence"
                ],
                "answer": "a tree with apples on it"
            },
            {
                "image": "static/images/page8_image6.png",
                "question": "What does this image show?",
                "caption": "a diagram of a single - pole",
                "options": [
                    "a diagram of a single - pole",
                    "A clock",
                    "A grid of shapes",
                    "A number sequence"
                ],
                "answer": "a diagram of a single - pole"
            },
            {
                "image": "static/images/page8_image7.png",
                "question": "What does this image show?",
                "caption": "a diagram of a single - pole",
                "options": [
                    "a diagram of a single - pole",
                    "A clock",
                    "A grid of shapes",
                    "A number sequence"
                ],
                "answer": "a diagram of a single - pole"
            },
            {
                "image": "static/images/page8_image8.png",
                "question": "What does this image show?",
                "caption": "a diagram of a single pole with a single pole",
                "options": [
                    "a diagram of a single pole with a single pole",
                    "A clock",
                    "A grid of shapes",
                    "A number sequence"
                ],
                "answer": "a diagram of a single pole with a single pole"
            },
            {
                "image": "static/images/page8_image9.png",
                "question": "What does this image show?",
                "caption": "a diagram of a single - pole",
                "options": [
                    "a diagram of a single - pole",
                    "A clock",
                    "A grid of shapes",
                    "A number sequence"
                ],
                "answer": "a diagram of a single - pole"
            }
        ]
    },
    {
        "page": 9,
        "text": "9 \n \n21. Which of the following is smallest? \n \n \nAns [C] \n \n22. 6 hundreds 3 tens 2 ones – 3 hundreds 2 tens 6 ones = \n____________. \n \n[A] 306 \n[B] 360 \n \n[C] 603 \n[D] 305 \nAns [A] \n \n23. \n \n   \n \n \nWhat does  \n  stand for ? \n \n[A] 7 \n[B] 5 \n \n[C] 3 \n[D] 4 \nAns [D] \n \n24. A number bond is shown below. \n \nWhat is the value of M × N? \n \n \n[A] 35 \n[B] 43 \n \n[C] 52 \n[D] 25",
        "images": [
            "static/images/page9_image1.jpeg",
            "static/images/page9_image2.png",
            "static/images/page9_image3.png",
            "static/images/page9_image4.png",
            "static/images/page9_image5.png",
            "static/images/page9_image6.png"
        ],
        "ai_generated_questions": [
            {
                "image": "static/images/page9_image1.jpeg",
                "question": "What does this image show?",
                "caption": "a white and orange check marke",
                "options": [
                    "a white and orange check marke",
                    "A clock",
                    "A grid of shapes",
                    "A number sequence"
                ],
                "answer": "a white and orange check marke"
            },
            {
                "image": "static/images/page9_image2.png",
                "question": "What does this image show?",
                "caption": "the number of the numbers in the numbers",
                "options": [
                    "the number of the numbers in the numbers",
                    "A clock",
                    "A grid of shapes",
                    "A number sequence"
                ],
                "answer": "the number of the numbers in the numbers"
            },
            {
                "image": "static/images/page9_image3.png",
                "question": "What does this image show?",
                "caption": "a white and black line shows the number of the two different parts",
                "options": [
                    "a white and black line shows the number of the two different parts",
                    "A clock",
                    "A grid of shapes",
                    "A number sequence"
                ],
                "answer": "a white and black line shows the number of the two different parts"
            },
            {
                "image": "static/images/page9_image4.png",
                "question": "What does this image show?",
                "caption": "a glass with a black handle and two glasses with a white background",
                "options": [
                    "a glass with a black handle and two glasses with a white background",
                    "A clock",
                    "A grid of shapes",
                    "A number sequence"
                ],
                "answer": "a glass with a black handle and two glasses with a white background"
            },
            {
                "image": "static/images/page9_image5.png",
                "question": "What does this image show?",
                "caption": "a black mug with the words, ` ` ' and ` ' ' '",
                "options": [
                    "a black mug with the words, ` ` ' and ` ' ' '",
                    "A clock",
                    "A grid of shapes",
                    "A number sequence"
                ],
                "answer": "a black mug with the words, ` ` ' and ` ' ' '"
            },
            {
                "image": "static/images/page9_image6.png",
                "question": "What does this image show?",
                "caption": "a diagram of the three aminos",
                "options": [
                    "a diagram of the three aminos",
                    "A clock",
                    "A grid of shapes",
                    "A number sequence"
                ],
                "answer": "a diagram of the three aminos"
            }
        ]
    },
    {
        "page": 10,
        "text": "10 \n \nAns [D] \n \n25. Tanya has following two pencils. \n \n \n \n \nFind the total length of both the pencils. \n \n[A] 7 units \n[B] 6 units \n \n[C] 5 units \n[D] 9 units \nAns [D] \n \n26. There were 298 hens and cows on a farm. \n \nThere were 153 hens. \n \nHow many cows were there? \n \n[A] 138 \n[B] 140 \n \n[C] 145 \n[D] 144 \nAns [C] \n \n27. Write the correct time for the clock shown below. \n \n \n[A] 5 : 15 \n[B] 5 : 40 \n \n[C] 6 : 20 \n[D] 3 : 20 \nAns [A]",
        "images": [
            "static/images/page10_image1.jpeg",
            "static/images/page10_image2.png",
            "static/images/page10_image3.png",
            "static/images/page10_image4.png"
        ],
        "ai_generated_questions": [
            {
                "image": "static/images/page10_image1.jpeg",
                "question": "What does this image show?",
                "caption": "a white and orange check marke",
                "options": [
                    "a white and orange check marke",
                    "A clock",
                    "A grid of shapes",
                    "A number sequence"
                ],
                "answer": "a white and orange check marke"
            },
            {
                "image": "static/images/page10_image2.png",
                "question": "What does this image show?",
                "caption": "a pencil and a pencil with a line of arrows",
                "options": [
                    "a pencil and a pencil with a line of arrows",
                    "A clock",
                    "A grid of shapes",
                    "A number sequence"
                ],
                "answer": "a pencil and a pencil with a line of arrows"
            },
            {
                "image": "static/images/page10_image3.png",
                "question": "What does this image show?",
                "caption": "the logo for the new website",
                "options": [
                    "the logo for the new website",
                    "A clock",
                    "A grid of shapes",
                    "A number sequence"
                ],
                "answer": "the logo for the new website"
            },
            {
                "image": "static/images/page10_image4.png",
                "question": "What does this image show?",
                "caption": "a clock with a white face and a black face",
                "options": [
                    "a clock with a white face and a black face",
                    "A clock",
                    "A grid of shapes",
                    "A number sequence"
                ],
                "answer": "a clock with a white face and a black face"
            }
        ]
    },
    {
        "page": 11,
        "text": "11 \n \n28. Sumit has following flowers and balloons. \n \n \n \nWhich statement is true? \n \n[A] Flowers are more than balloons. \n \n[B] Flowers are equal to balloons. \n \n[C] Flowers are less than balloons \n \n[D] Balloons are 2 more than flowers. \nAns [C] \n \n29. A bag of rice weighs 3 kg. How much do 6 bags of rice \nweight? \n \n[A] 18 kg \n[B] 24 kg \n \n[C] 15 kg \n[D] 17 kg \nAns [A] \n \n30. If only all Saturdays and Sundays are holidays, then in the \nmonth of December 2014 how many holidays will we get? \n \n \n \n[A] 6 \n[B] 8 \n \n[C] 10 \n[D] 7",
        "images": [
            "static/images/page11_image1.jpeg",
            "static/images/page11_image2.png",
            "static/images/page11_image3.png",
            "static/images/page11_image4.jpeg"
        ],
        "ai_generated_questions": [
            {
                "image": "static/images/page11_image1.jpeg",
                "question": "What does this image show?",
                "caption": "a white and orange check marke",
                "options": [
                    "a white and orange check marke",
                    "A clock",
                    "A grid of shapes",
                    "A number sequence"
                ],
                "answer": "a white and orange check marke"
            },
            {
                "image": "static/images/page11_image2.png",
                "question": "What does this image show?",
                "caption": "a drawing of a line of lines that are drawn in different directions",
                "options": [
                    "a drawing of a line of lines that are drawn in different directions",
                    "A clock",
                    "A grid of shapes",
                    "A number sequence"
                ],
                "answer": "a drawing of a line of lines that are drawn in different directions"
            },
            {
                "image": "static/images/page11_image3.png",
                "question": "What does this image show?",
                "caption": "a set of blue balloons with a white background",
                "options": [
                    "a set of blue balloons with a white background",
                    "A clock",
                    "A grid of shapes",
                    "A number sequence"
                ],
                "answer": "a set of blue balloons with a white background"
            },
            {
                "image": "static/images/page11_image4.jpeg",
                "question": "What does this image show?",
                "caption": "a calendar with the date of december",
                "options": [
                    "a calendar with the date of december",
                    "A clock",
                    "A grid of shapes",
                    "A number sequence"
                ],
                "answer": "a calendar with the date of december"
            }
        ]
    },
    {
        "page": 12,
        "text": "12 \n \nAns [B] \n \nACHIEVER SECTION \n \n31. How much do the counters add up to? \n \n \n[A] 253 \n[B] 235 \n \n[C] 325 \n[D] 532 \nAns [A] \n \n32. The packet of rice has a mass of _______________ kg. \n \nFlour\n0\n5\n10\n15",
        "images": [
            "static/images/page12_image1.jpeg",
            "static/images/page12_image2.png"
        ],
        "ai_generated_questions": [
            {
                "image": "static/images/page12_image1.jpeg",
                "question": "What does this image show?",
                "caption": "a white and orange check marke",
                "options": [
                    "a white and orange check marke",
                    "A clock",
                    "A grid of shapes",
                    "A number sequence"
                ],
                "answer": "a white and orange check marke"
            },
            {
                "image": "static/images/page12_image2.png",
                "question": "What does this image show?",
                "caption": "a diagram of the number of the two - dimensional numbers",
                "options": [
                    "a diagram of the number of the two - dimensional numbers",
                    "A clock",
                    "A grid of shapes",
                    "A number sequence"
                ],
                "answer": "a diagram of the number of the two - dimensional numbers"
            }
        ]
    },
    {
        "page": 13,
        "text": "13 \n \n \n[A] 9 \n[B] 15 \n \n[C] 18 \n[D] 12 \nAns [D] \n \n33. Fill in the blank:  \n \nThe book is ________________ the lamp. \n \n \n \n[A]Equal to  \n[B] Lighter than \n \n[C] Heavier than [D] None of these \nAns [B] \n \n34. Which of the following is the CORRECT way of writing 8 \nless than 14? \n \n[A] 14 – 8 = 6 \n[B] 14 + 8 = 6 \n \n[C] 14 – 6 = 8 \n[D] 14 + 6 = 8 \nAns [A] \n \n35. Tonu gave Rs 50 to buy this ball. How much money will he \nget back? \n \n \n[A]  Rs 15 \n[B]Rs  25 \n \n[C]   Rs 20 \n[D]   Rs 17",
        "images": [
            "static/images/page13_image1.jpeg",
            "static/images/page13_image2.png",
            "static/images/page13_image3.png"
        ],
        "ai_generated_questions": [
            {
                "image": "static/images/page13_image1.jpeg",
                "question": "What does this image show?",
                "caption": "a white and orange check marke",
                "options": [
                    "a white and orange check marke",
                    "A clock",
                    "A grid of shapes",
                    "A number sequence"
                ],
                "answer": "a white and orange check marke"
            },
            {
                "image": "static/images/page13_image2.png",
                "question": "What does this image show?",
                "caption": "a scale with a lamp and a book on it",
                "options": [
                    "a scale with a lamp and a book on it",
                    "A clock",
                    "A grid of shapes",
                    "A number sequence"
                ],
                "answer": "a scale with a lamp and a book on it"
            },
            {
                "image": "static/images/page13_image3.png",
                "question": "What does this image show?",
                "caption": "a beach ball with a number on it",
                "options": [
                    "a beach ball with a number on it",
                    "A clock",
                    "A grid of shapes",
                    "A number sequence"
                ],
                "answer": "a beach ball with a number on it"
            }
        ]
    },
    {
        "page": 14,
        "text": "14 \n \nAns [B]",
        "images": [
            "static/images/page14_image1.jpeg"
        ],
        "ai_generated_questions": [
            {
                "image": "static/images/page14_image1.jpeg",
                "question": "What does this image show?",
                "caption": "a white and orange check marke",
                "options": [
                    "a white and orange check marke",
                    "A clock",
                    "A grid of shapes",
                    "A number sequence"
                ],
                "answer": "a white and orange check marke"
            }
        ]
    }
]